oeleo/__init__.py
oeleo/checkers.py
oeleo/connectors.py
oeleo/console.py
oeleo/filters.py
oeleo/main.py
oeleo/models.py
oeleo/movers.py
oeleo/reporters.py
oeleo/schedulers.py
oeleo/utils.py
oeleo/workers.py
oeleo-0.7.0.dist-info/METADATA
oeleo-0.7.0.dist-info/WHEEL
oeleo-0.7.0.dist-info/licenses/LICENSE.md
oeleo-0.7.0.dist-info/RECORD
