Metadata-Version: 2.4
Name: oeleo
Version: 0.7.0
Summary: A one-eyed tool to copy files with.
Project-URL: Homepage, https://github.com/ife-bat/oeleo
Project-URL: Repository, https://github.com/ife-bat/oeleo
Author-email: jepegit <jepe@ife.no>
License: MIT
License-File: LICENSE.md
Keywords: db,ssh
Classifier: Environment :: Console
Classifier: Intended Audience :: Other Audience
Classifier: Intended Audience :: Science/Research
Classifier: Operating System :: OS Independent
Classifier: Topic :: Communications :: File Sharing
Classifier: Topic :: Home Automation
Classifier: Topic :: Software Development :: Documentation
Classifier: Topic :: System :: Networking
Classifier: Topic :: Utilities
Requires-Python: <3.13,>=3.8
Requires-Dist: fabric
Requires-Dist: peewee
Requires-Dist: python-dotenv
Requires-Dist: rich
Requires-Dist: shareplum
Provides-Extra: all
Requires-Dist: pystray<0.20.0,>=0.19.5; extra == 'all'
